{
  "name": "Bone Knife",
  "description": "Defend yourself with this small (but sharp) bone shard.",
  "obstructsMovement": false,
  "allowsPickup": true,
  "health": 10,
  "craftingRequirements": [
    { "id": "twine", "quantity": 1 },
    { "id": "rock", "quantity": 1 },
    { "id": "bone", "quantity": 1 }
  ],
  "usage": {
    "type": "equippable",
    "slot": "weapon",
    "usageLimit": 8
  },
  "attack": {
    "stamina": 4,
    "health": 0,
    "strength": 4,
    "damage": 4,
    "frameSpeed": 50,
    "sound": "sounds/knifesword-swish.mp3",
    "soundDelay": 500,
    "position": "floor",
    "frames": [
      [
        "@@@@@@@@@@@@@@@@@@@@@@@@@",
        "@@@@@@@@@@@@@@@@@@@@@@@@@",
        "@@@@@@@@@@@@@@@@@@@@@@@@@",
        "@@@@@@@@@@@@@@@@@@@@@@@@@",
        "@@@@@@@@@@@@@@@@@@@@@@@@@",
        "@@@@@@@@@@@@@@@@@@@@@@^@@",
        "@@@@@@@@@@@@@@@@@@@@@|/|@"
      ],
      [
        "@@@@@@@@@@@@@@@@@@@@@@@@@",
        "@@@@@@@@@@@@@@@@@@@@@@@@@",
        "@@@@@@@@@@@@@@@@@@@@@@@@@",
        "@@@@@@@@@@@@@@@@@@@@@@@@@",
        "@@@@@@@@@@@@@@@@@@@@^@@@@",
        "@@@@@@@@@@@@@@@@@@@|/|@@@",
        "@@@@@@@@@@@@@@@@@@@|/|@@@"
      ],
      [
        "@@@@@@@@@@@@@@@@@@@@@@@@@",
        "@@@@@@@@@@@@@@@@@@@@@@@@@",
        "@@@@@@@@@@@@@@@@@@@@@@@@@",
        "@@@@@@@@@@@@@@@@@^.@@@@@@",
        "@@@@@@@@@@@@@@@@//|@@@@@@",
        "@@@@@@@@@@@@@@@@|/|@@@@@@",
        "@@@@@@@@@@@@@@@@|/|@@@@@@"
      ],
      [
        "@@@@@@@@@@@@@@@@@@@@@@@@@",
        "@@@@@@@@@@@@@@@@@@@@@@@@@",
        "@@@@@@@@@@@@@@^.@@@@@@@@@",
        "@@@@@@@@@@@@@//|@@@@@@@@@",
        "@@@@@@@@@@@@@|/|@@@@@@@@@",
        "@@@@@@@@@@@@@|/|@@@@@@@@@",
        "@@@@@@@@@@@@@|/|@@@@@@@@@"
      ],
      [
        "@@@@@@@@@@@@@@^.@@@@@@@@@",
        "@@@@@@@@@@@@@//|@@@@@@@@@",
        "@@@@@@@@@@@@@|/|@@@@@@@@@",
        "@@@@@@@@@@@@@|/|@@@@@@@@@",
        "@@@@@@@@@@@@@|/|@@@@@@@@@",
        "@@@@@@@@@@@@@|/|@@@@@@@@@",
        "@@@@@@@@@@@@@|/|@@@@@@@@@"
      ],
      [
        "@@@@@@@@@@@@@@@@@@@@@@@@@",
        "@@@@@@@@@@@@@@@@@@@@@@@@@",
        "@@@@@@@@@@@@@@^.@@@@@@@@@",
        "@@@@@@@@@@@@@//|@@@@@@@@@",
        "@@@@@@@@@@@@@|/|@@@@@@@@@",
        "@@@@@@@@@@@@@|/|@@@@@@@@@",
        "@@@@@@@@@@@@@|/|@@@@@@@@@"
      ],
      [
        "@@@@@@@@@@@@@@@@@@@@@@@@@",
        "@@@@@@@@@@@@@@@@@@@@@@@@@",
        "@@@@@@@@@@@@@@@@@@@@@@@@@",
        "@@@@@@@@@@@@@@@@@^.@@@@@@",
        "@@@@@@@@@@@@@@@@//|@@@@@@",
        "@@@@@@@@@@@@@@@@|/|@@@@@@",
        "@@@@@@@@@@@@@@@@|/|@@@@@@"
      ],
      [
        "@@@@@@@@@@@@@@@@@@@@@@@@@",
        "@@@@@@@@@@@@@@@@@@@@@@@@@",
        "@@@@@@@@@@@@@@@@@@@@@@@@@",
        "@@@@@@@@@@@@@@@@@@@@@@@@@",
        "@@@@@@@@@@@@@@@@@@@@^@@@@",
        "@@@@@@@@@@@@@@@@@@@|/|@@@",
        "@@@@@@@@@@@@@@@@@@@|/|@@@"
      ],
      [
        "@@@@@@@@@@@@@@@@@@@@@@@@@",
        "@@@@@@@@@@@@@@@@@@@@@@@@@",
        "@@@@@@@@@@@@@@@@@@@@@@@@@",
        "@@@@@@@@@@@@@@@@@@@@@@@@@",
        "@@@@@@@@@@@@@@@@@@@@@@@@@",
        "@@@@@@@@@@@@@@@@@@@@@@^@@",
        "@@@@@@@@@@@@@@@@@@@@@|/|@"
      ],
      [
        "@@@@@@@@@@@@@@@@@@@@@@@@@",
        "@@@@@@@@@@@@@@@@@@@@@@@@@",
        "@@@@@@@@@@@@@@@@@@@@@@@@@",
        "@@@@@@@@@@@@@@@@@@@@@@@@@",
        "@@@@@@@@@@@@@@@@@@@@@@@@@",
        "@@@@@@@@@@@@@@@@@@@@@@@@@",
        "@@@@@@@@@@@@@@@@@@@@@@@@@"
      ]
    ]
  },
  "perspective": {
    "midRange": {
      "position": "floor",
      "frames": [["-‧"]]
    },
    "nearby": {
      "position": "floor",
      "frames": [[":-:--‧"]]
    },
    "here": {
      "message": "You see a knife made of bone laying on the ground.",
      "position": "floor",
      "frames": [
        [
          "@_@@@@@_@@@@@@@⎽", 
          "(_'⎯⎯⎯' '⎻⎺⎺⎺⎺⎺╱", 
          "(_.⎯⎯⎯._.⎼⎼⎻⎺⎺⎺@"
          ]
        ]
    }
  }
}
